odoo10_addon_l10n_nl_bank-10.0.1.0.0-py2.7-nspkg.pth
odoo/addons/l10n_nl_bank/README.rst
odoo/addons/l10n_nl_bank/__init__.py
odoo/addons/l10n_nl_bank/__manifest__.py
odoo/addons/l10n_nl_bank/data/res_bank_data.xml
odoo/addons/l10n_nl_bank/static/description/icon.png
odoo10_addon_l10n_nl_bank-10.0.1.0.0.dist-info/DESCRIPTION.rst
odoo10_addon_l10n_nl_bank-10.0.1.0.0.dist-info/METADATA
odoo10_addon_l10n_nl_bank-10.0.1.0.0.dist-info/RECORD
odoo10_addon_l10n_nl_bank-10.0.1.0.0.dist-info/WHEEL
odoo10_addon_l10n_nl_bank-10.0.1.0.0.dist-info/metadata.json
odoo10_addon_l10n_nl_bank-10.0.1.0.0.dist-info/namespace_packages.txt
odoo10_addon_l10n_nl_bank-10.0.1.0.0.dist-info/top_level.txt
